accl/__init__.py
accl/api/__init__.py
accl/api/app.py
accl/api/schemas.py
accl/api/service.py
accl/api/storage.py
accl/configs/__init__.py
accl/configs/model_config.yaml
accl/configs/prompt_templates.yaml
accl/configs/template_config.yaml
accl/ctxbuild/__init__.py
accl/ctxbuild/angle_ctxbuilder.py
accl/ctxbuild/base.py
accl/ctxbuild/chart_ctxbuilder.py
accl/ctxbuild/dtctx_builder.py
accl/ctxbuild/registry.py
accl/generator/__init__.py
accl/generator/base.py
accl/generator/llm_parser.py
accl/generator/qgen.py
accl/generator/template.py
accl/llm/__init__.py
accl/llm/base.py
accl/llm/gemini.py
accl/llm/gpts.py
accl/optimizer/__init__.py
accl/pipeline/handler.py
accl/pipeline/runner.py
accl/pipeline/runplan.py
accl/render/__init__.py
accl/render/angle_render.py
accl/render/base.py
accl/render/chart_render.py
accl/render/datatable_render.py
accl/schemas/__init__.py
accl/schemas/angle.py
accl/schemas/base.py
accl/schemas/chart.py
accl/schemas/datatable.py
accl/utils/config_loader.py
accl/utils/num_gen.py
accl/utils/prompt_loader.py
accl/utils/rate_limiter.py
accl/utils/savecsv.py
accl/utils/savejson.py
accl/utils/token_logger.py
accl/utils/tools.py
accl-0.1.0.dist-info/METADATA
accl-0.1.0.dist-info/WHEEL
accl-0.1.0.dist-info/RECORD
