Metadata-Version: 2.1
Name: accl
Version: 0.1.0
Summary: 
Author: yukesh-ix
Author-email: yukesh.nepal@olivegroup.io
Requires-Python: >=3.12,<4.0
Classifier: Programming Language :: Python :: 3
Classifier: Programming Language :: Python :: 3.12
Requires-Dist: dynaconf (>=3.2.12,<4.0.0)
Requires-Dist: fastapi (>=0.124.0,<0.125.0)
Requires-Dist: google-api-core (>=2.28.1,<3.0.0)
Requires-Dist: google-genai (>=1.53.0,<2.0.0)
Requires-Dist: ipywidgets (>=8.1.8,<9.0.0)
Requires-Dist: langchain[google-genai] (>=1.0.8,<2.0.0)
Requires-Dist: seaborn (>=0.13.2,<0.14.0)
Requires-Dist: tqdm (>=4.67.1,<5.0.0)
Requires-Dist: uvicorn (>=0.38.0,<0.39.0)
